src/Predict.sv
import Common::*;

module Predict (
    input act_func activation,
    input real sum,
    output real prediction
);

    always_comb begin
        case (activation)
            Identity: begin
                prediction = sum;
            end
            Heaviside_Step: begin
                prediction = (sum > 0);
            end
            ReLU: begin
                prediction = (sum > 0) ? sum : 0;
            end
        endcase
    end

endmodule

src/PerceptronIntroduction.sv
import Common::*;

module PerceptronIntroduction #(
    parameter int size = 2,
    parameter int num  = 4
) (
    input logic clk,
    input real values[size-1:0],
    input act_func activation,
    output real prediction,
    output logic training,
    input int epochs,
    input real learning_rate,
    input real train_values[num-1:0][size-1:0],
    input real expected[num-1:0]
);
    real weights[size-1:0];
    real bias;

    initial begin
        for (int i = 0; i < size; i++) begin
            weights[i] = 0;
        end
        bias = 0;
    end

    real sum;

    always_comb begin
        sum = bias;
        for (int i = 0; i < size; i++) begin
            sum += weights[i] * values[i];
        end
    end

    Predict predict (
        .activation(activation),
        .sum(sum),
        .prediction(prediction)
    );


    train_state state = Idle;
    real train_prediction;
    real train_sum;
    int epoch_count = 0;
    int sample_idx = 0;
    real error;

    always_comb begin
        train_sum = bias;
        for (int i = 0; i < size; i++) begin
            train_sum += weights[i] * train_values[sample_idx][i];
        end
    end

    Predict train_predict (
        .activation(activation),
        .sum(train_sum),
        .prediction(train_prediction)
    );

    always_ff @(posedge clk) begin
        if (training) begin
            case (state)
                Idle: begin
                    sample_idx <= 0;
                    state <= Compute;
                end

                Compute: begin
                    error <= expected[sample_idx] - train_prediction;
                    state <= Update;
                end

                Update: begin
                    for (int i = 0; i < size; i++) begin
                        weights[i] <= weights[i] + learning_rate * error * train_values[sample_idx][i];
                    end
                    bias <= bias + learning_rate * error;

                    if (sample_idx < num - 1) begin
                        sample_idx <= sample_idx + 1;
                        state <= Compute;
                    end else begin
                        sample_idx <= 0;
                        if (epoch_count < epochs - 1) begin
                            epoch_count <= epoch_count + 1;
                            state <= Compute;
                        end else begin
                            training <= 0;
                            state <= Idle;
                        end
                    end
                end
            endcase
        end
    end

    //figure out backpropagation

endmodule

src/Benches/BenchPerceptronIntroduction.sv
import Common::*;

module BenchPerceptronIntroduction ();

    bit clk;
    parameter int size = 2;
    parameter int num = 4;
    real values[size-1:0];
    act_func activation = Heaviside_Step;
    real prediction;
    bit training = 1;
    int epochs = 10;
    real learning_rate = 1;
    real train_values[num-1:0][size-1:0] = '{'{0.0, 0.0}, '{0.0, 1.0}, '{1.0, 0.0}, '{1.0, 1.0}};
    //AND
    real expected[num-1:0] = '{0.0, 0.0, 0.0, 1.0};
    //OR
    //real expected[num-1:0] = '{0.0, 1.0, 1.0, 1.0};
    //NAND
    //real expected[num-1:0] = '{1.0, 1.0, 1.0, 0.0};
    //XOR (should fail)
    //real expected[num-1:0] = '{0.0, 1.0, 1.0, 0.0};


    PerceptronIntroduction #(
        .size(size),
        .num (num)
    ) perceptron_i (
        .clk(clk),
        .values(values),
        .activation(activation),
        .prediction(prediction),
        .training(training),
        .epochs(epochs),
        .learning_rate(learning_rate),
        .train_values(train_values),
        .expected(expected)
    );

    initial begin
        $dumpfile("sim.vcd");
        $dumpvars;
        clk = 0;
        forever begin
            #1 clk = ~clk;
        end
    end

    initial begin
        wait (training == 0);
        #10;
        values[0] = 0.0;
        values[1] = 0.0;
        #5 values[0] = 1.0;
        values[1] = 0.0;
        #5 values[0] = 0.0;
        values[1] = 1.0;
        #5 values[0] = 1.0;
        values[1] = 1.0;
        #5 $finish;
    end

endmodule

sim.vcd
$version Generated by VerilatedVcd $end
$timescale 1ps $end
 $scope module $rootio $end
 $upscope $end
 $scope module BenchPerceptronIntroduction $end
  $var wire 1 F clk $end
  $var wire 32 V size [31:0] $end
  $var wire 32 W num [31:0] $end
  $var real 64 G values[0] $end
  $var real 64 I values[1] $end
  $var wire 32 X activation [31:0] $end
  $var real 64 K prediction $end
  $var wire 1 ; training $end
  $var wire 32 Y epochs [31:0] $end
  $var real 64 Z learning_rate $end
  $var real 64 # train_values[0][0] $end
  $var real 64 % train_values[0][1] $end
  $var real 64 ' train_values[1][0] $end
  $var real 64 ) train_values[1][1] $end
  $var real 64 + train_values[2][0] $end
  $var real 64 - train_values[2][1] $end
  $var real 64 / train_values[3][0] $end
  $var real 64 1 train_values[3][1] $end
  $var real 64 3 expected[0] $end
  $var real 64 5 expected[1] $end
  $var real 64 7 expected[2] $end
  $var real 64 9 expected[3] $end
  $scope module perceptron_i $end
   $var wire 32 V size [31:0] $end
   $var wire 32 W num [31:0] $end
   $var wire 1 F clk $end
   $var real 64 G values[0] $end
   $var real 64 I values[1] $end
   $var wire 32 X activation [31:0] $end
   $var real 64 K prediction $end
   $var wire 1 ; training $end
   $var wire 32 Y epochs [31:0] $end
   $var real 64 Z learning_rate $end
   $var real 64 # train_values[0][0] $end
   $var real 64 % train_values[0][1] $end
   $var real 64 ' train_values[1][0] $end
   $var real 64 ) train_values[1][1] $end
   $var real 64 + train_values[2][0] $end
   $var real 64 - train_values[2][1] $end
   $var real 64 / train_values[3][0] $end
   $var real 64 1 train_values[3][1] $end
   $var real 64 3 expected[0] $end
   $var real 64 5 expected[1] $end
   $var real 64 7 expected[2] $end
   $var real 64 9 expected[3] $end
   $var real 64 M weights[0] $end
   $var real 64 O weights[1] $end
   $var real 64 Q bias $end
   $var real 64 S sum $end
   $var wire 32 < state [31:0] $end
   $var real 64 = train_prediction $end
   $var real 64 ? train_sum $end
   $var wire 32 A epoch_count [31:0] $end
   $var wire 32 B sample_idx [31:0] $end
   $var real 64 C error $end
   $scope module predict $end
    $var wire 32 X activation [31:0] $end
    $var real 64 S sum $end
    $var real 64 K prediction $end
   $upscope $end
   $scope module train_predict $end
    $var wire 32 X activation [31:0] $end
    $var real 64 ? sum $end
    $var real 64 = prediction $end
   $upscope $end
   $scope module unnamedblk1 $end
    $var wire 32 U i [31:0] $end
   $upscope $end
   $scope module unnamedblk2 $end
    $var wire 32 \ i [31:0] $end
   $upscope $end
   $scope module unnamedblk3 $end
    $var wire 32 \ i [31:0] $end
   $upscope $end
   $scope module unnamedblk4 $end
    $var wire 32 E i [31:0] $end
   $upscope $end
  $upscope $end
 $upscope $end
$enddefinitions $end


#0
r1 #
r1 %
r0 '
r1 )
r1 +
r0 -
r0 /
r0 1
r1 3
r0 5
r0 7
r0 9
1;
b00000000000000000000000000000000 <
r0 =
r0 ?
b00000000000000000000000000000000 A
b00000000000000000000000000000000 B
r0 C
b00000000000000000000000000000000 E
0F
r0 G
r0 I
r0 K
r0 M
r0 O
r0 Q
r0 S
b00000000000000000000000000000010 U
b00000000000000000000000000000010 V
b00000000000000000000000000000100 W
b00000000000000000000000000000001 X
b00000000000000000000000000001010 Y
r1 Z
b00000000000000000000000000000010 \
#1
b00000000000000000000000000000001 <
1F
#2
0F
#3
b00000000000000000000000000000010 <
r1 C
1F
#4
0F
#5
b00000000000000000000000000000001 <
r1 =
r2 ?
b00000000000000000000000000000001 B
b00000000000000000000000000000010 E
1F
r1 K
r1 M
r1 O
r1 Q
r1 S
#6
0F
#7
b00000000000000000000000000000010 <
r-1 C
1F
#8
0F
#9
b00000000000000000000000000000001 <
r1 ?
b00000000000000000000000000000010 B
1F
r0 K
r0 O
r0 Q
r0 S
#10
0F
#11
b00000000000000000000000000000010 <
1F
#12
0F
#13
b00000000000000000000000000000001 <
r0 =
r-1 ?
b00000000000000000000000000000011 B
1F
r0 M
r-1 Q
r-1 S
#14
0F
#15
b00000000000000000000000000000010 <
r0 C
1F
#16
0F
#17
b00000000000000000000000000000001 <
b00000000000000000000000000000001 A
b00000000000000000000000000000000 B
1F
#18
0F
#19
b00000000000000000000000000000010 <
r1 C
1F
#20
0F
#21
b00000000000000000000000000000001 <
r1 =
r1 ?
b00000000000000000000000000000001 B
1F
r1 M
r1 O
r0 Q
r0 S
#22
0F
#23
b00000000000000000000000000000010 <
r-1 C
1F
#24
0F
#25
b00000000000000000000000000000001 <
r0 =
r0 ?
b00000000000000000000000000000010 B
1F
r0 O
r-1 Q
r-1 S
#26
0F
#27
b00000000000000000000000000000010 <
r0 C
1F
#28
0F
#29
b00000000000000000000000000000001 <
r-1 ?
b00000000000000000000000000000011 B
1F
#30
0F
#31
b00000000000000000000000000000010 <
1F
#32
0F
#33
b00000000000000000000000000000001 <
r0 ?
b00000000000000000000000000000010 A
b00000000000000000000000000000000 B
1F
#34
0F
#35
b00000000000000000000000000000010 <
r1 C
1F
#36
0F
#37
b00000000000000000000000000000001 <
r1 =
r1 ?
b00000000000000000000000000000001 B
1F
r2 M
r1 O
r0 Q
r0 S
#38
0F
#39
b00000000000000000000000000000010 <
r-1 C
1F
#40
0F
#41
b00000000000000000000000000000001 <
b00000000000000000000000000000010 B
1F
r0 O
r-1 Q
r-1 S
#42
0F
#43
b00000000000000000000000000000010 <
1F
#44
0F
#45
b00000000000000000000000000000001 <
r0 =
r-2 ?
b00000000000000000000000000000011 B
1F
r1 M
r-2 Q
r-2 S
#46
0F
#47
b00000000000000000000000000000010 <
r0 C
1F
#48
0F
#49
b00000000000000000000000000000001 <
r-1 ?
b00000000000000000000000000000011 A
b00000000000000000000000000000000 B
1F
#50
0F
#51
b00000000000000000000000000000010 <
r1 C
1F
#52
0F
#53
b00000000000000000000000000000001 <
r0 ?
b00000000000000000000000000000001 B
1F
r2 M
r1 O
r-1 Q
r-1 S
#54
0F
#55
b00000000000000000000000000000010 <
r0 C
1F
#56
0F
#57
b00000000000000000000000000000001 <
r1 =
r1 ?
b00000000000000000000000000000010 B
1F
#58
0F
#59
b00000000000000000000000000000010 <
r-1 C
1F
#60
0F
#61
b00000000000000000000000000000001 <
r0 =
r-2 ?
b00000000000000000000000000000011 B
1F
r1 M
r-2 Q
r-2 S
#62
0F
#63
b00000000000000000000000000000010 <
r0 C
1F
#64
0F
#65
b00000000000000000000000000000001 <
r0 ?
b00000000000000000000000000000100 A
b00000000000000000000000000000000 B
1F
#66
0F
#67
b00000000000000000000000000000010 <
r1 C
1F
#68
0F
#69
b00000000000000000000000000000001 <
r1 =
r1 ?
b00000000000000000000000000000001 B
1F
r2 M
r2 O
r-1 Q
r-1 S
#70
0F
#71
b00000000000000000000000000000010 <
r-1 C
1F
#72
0F
#73
b00000000000000000000000000000001 <
r0 =
r0 ?
b00000000000000000000000000000010 B
1F
r1 O
r-2 Q
r-2 S
#74
0F
#75
b00000000000000000000000000000010 <
r0 C
1F
#76
0F
#77
b00000000000000000000000000000001 <
r-2 ?
b00000000000000000000000000000011 B
1F
#78
0F
#79
b00000000000000000000000000000010 <
1F
#80
0F
#81
b00000000000000000000000000000001 <
r1 =
r1 ?
b00000000000000000000000000000101 A
b00000000000000000000000000000000 B
1F
#82
0F
#83
b00000000000000000000000000000010 <
1F
#84
0F
#85
b00000000000000000000000000000001 <
r0 =
r-1 ?
b00000000000000000000000000000001 B
1F
#86
0F
#87
b00000000000000000000000000000010 <
1F
#88
0F
#89
b00000000000000000000000000000001 <
r0 ?
b00000000000000000000000000000010 B
1F
#90
0F
#91
b00000000000000000000000000000010 <
1F
#92
0F
#93
b00000000000000000000000000000001 <
r-2 ?
b00000000000000000000000000000011 B
1F
#94
0F
#95
b00000000000000000000000000000010 <
1F
#96
0F
#97
b00000000000000000000000000000001 <
r1 =
r1 ?
b00000000000000000000000000000110 A
b00000000000000000000000000000000 B
1F
#98
0F
#99
b00000000000000000000000000000010 <
1F
#100
0F
#101
b00000000000000000000000000000001 <
r0 =
r-1 ?
b00000000000000000000000000000001 B
1F
#102
0F
#103
b00000000000000000000000000000010 <
1F
#104
0F
#105
b00000000000000000000000000000001 <
r0 ?
b00000000000000000000000000000010 B
1F
#106
0F
#107
b00000000000000000000000000000010 <
1F
#108
0F
#109
b00000000000000000000000000000001 <
r-2 ?
b00000000000000000000000000000011 B
1F
#110
0F
#111
b00000000000000000000000000000010 <
1F
#112
0F
#113
b00000000000000000000000000000001 <
r1 =
r1 ?
b00000000000000000000000000000111 A
b00000000000000000000000000000000 B
1F
#114
0F
#115
b00000000000000000000000000000010 <
1F
#116
0F
#117
b00000000000000000000000000000001 <
r0 =
r-1 ?
b00000000000000000000000000000001 B
1F
#118
0F
#119
b00000000000000000000000000000010 <
1F
#120
0F
#121
b00000000000000000000000000000001 <
r0 ?
b00000000000000000000000000000010 B
1F
#122
0F
#123
b00000000000000000000000000000010 <
1F
#124
0F
#125
b00000000000000000000000000000001 <
r-2 ?
b00000000000000000000000000000011 B
1F
#126
0F
#127
b00000000000000000000000000000010 <
1F
#128
0F
#129
b00000000000000000000000000000001 <
r1 =
r1 ?
b00000000000000000000000000001000 A
b00000000000000000000000000000000 B
1F
#130
0F
#131
b00000000000000000000000000000010 <
1F
#132
0F
#133
b00000000000000000000000000000001 <
r0 =
r-1 ?
b00000000000000000000000000000001 B
1F
#134
0F
#135
b00000000000000000000000000000010 <
1F
#136
0F
#137
b00000000000000000000000000000001 <
r0 ?
b00000000000000000000000000000010 B
1F
#138
0F
#139
b00000000000000000000000000000010 <
1F
#140
0F
#141
b00000000000000000000000000000001 <
r-2 ?
b00000000000000000000000000000011 B
1F
#142
0F
#143
b00000000000000000000000000000010 <
1F
#144
0F
#145
b00000000000000000000000000000001 <
r1 =
r1 ?
b00000000000000000000000000001001 A
b00000000000000000000000000000000 B
1F
#146
0F
#147
b00000000000000000000000000000010 <
1F
#148
0F
#149
b00000000000000000000000000000001 <
r0 =
r-1 ?
b00000000000000000000000000000001 B
1F
#150
0F
#151
b00000000000000000000000000000010 <
1F
#152
0F
#153
b00000000000000000000000000000001 <
r0 ?
b00000000000000000000000000000010 B
1F
#154
0F
#155
b00000000000000000000000000000010 <
1F
#156
0F
#157
b00000000000000000000000000000001 <
r-2 ?
b00000000000000000000000000000011 B
1F
#158
0F
#159
b00000000000000000000000000000010 <
1F
#160
0F
#161
0;
b00000000000000000000000000000000 <
r1 =
r1 ?
b00000000000000000000000000000000 B
1F
#162
0F
#163
1F
#164
0F
#165
1F
#166
0F
#167
1F
#168
0F
#169
1F
#170
0F
#171
1F
#172
0F
#173
1F
#174
0F
#175
1F
#176
0F
r1 G
r0 S
#177
1F
#178
0F
#179
1F
#180
0F
#181
1F
r0 G
r1 I
r-1 S
#182
0F
#183
1F
#184
0F
#185
1F
#186
0F
r1 G
r1 K
r1 S
